stcgal/__init__.py
stcgal/__main__.py
stcgal/frontend.py
stcgal/ihex.py
stcgal/models.py
stcgal/options.py
stcgal/protocols.py
stcgal/utils.py
stcgal-1.10.dist-info/METADATA
stcgal-1.10.dist-info/WHEEL
stcgal-1.10.dist-info/entry_points.txt
stcgal-1.10.dist-info/top_level.txt
stcgal-1.10.dist-info/RECORD
