Metadata-Version: 2.1
Name: stcgal
Version: 1.10
Summary: STC MCU ISP flash tool
Home-page: https://github.com/grigorig/stcgal
Author: Grigori Goronzy
Author-email: greg@kinoho.net
License: MIT License
Keywords: stc mcu microcontroller 8051 mcs-51
Platform: any
Classifier: Development Status :: 5 - Production/Stable
Classifier: Environment :: Console
Classifier: Intended Audience :: Developers
Classifier: License :: OSI Approved :: MIT License
Classifier: Operating System :: POSIX
Classifier: Operating System :: Microsoft :: Windows
Classifier: Operating System :: MacOS
Classifier: Programming Language :: Python :: 3
Classifier: Programming Language :: Python :: 3.5
Classifier: Programming Language :: Python :: 3.6
Classifier: Topic :: Software Development :: Embedded Systems
Classifier: Topic :: Software Development
Requires-Dist: pyserial (>=3.0)
Requires-Dist: tqdm (>=4.0.0)
Provides-Extra: usb
Requires-Dist: pyusb (>=1.0.0) ; extra == 'usb'
